{
  "errno": 0,
  "data": {
    "todaydata": {
      "fight": [
        {
          "name": "电销专员",
          "fightInfo": [
            {
              "name": "转正人数",
              "num": "481"
            },
            {
              "name": "离职率",
              "num": "3.22%"
            }
          ]
        },
        {
          "name": "渠道",
          "fightInfo": [
            {
              "name": "转正人数",
              "num": "451"
            }
          ]
        },
        {
          "name": "职能",
          "fightInfo": [
            {
              "name": "满编率",
              "num": "102.88%"
            },
            {
              "name": "离职率",
              "num": "1.57%"
            }
          ]
        }
      ],
      "feeuser": [
        {
          "name": "电销",
          "num": "35,386"
        },
        {
          "name": "渠道",
          "num": "24,464"
        },
        {
          "name": "行业",
          "num": "7,426"
        },
        {
          "name": "自助销售",
          "num": "447"
        }
      ],
      "main": [
        {
          "name": "IP",
          "num": "139,810"
        },
        {
          "name": "PV",
          "num": "650,903"
        },
        {
          "name": "UV",
          "num": "192,661"
        },
        {
          "name": "收费会员",
          "num": "67,723"
        }
      ]
    },
    "yesterdaydata": {
      "fight": [
        {
          "name": "电销专员",
          "fightInfo": [
            {
              "name": "转正人数",
              "num": "484"
            },
            {
              "name": "离职率",
              "num": "2.62%"
            }
          ]
        },
        {
          "name": "渠道",
          "fightInfo": [
            {
              "name": "转正人数",
              "num": "451"
            }
          ]
        },
        {
          "name": "职能",
          "fightInfo": [
            {
              "name": "满编率",
              "num": "102.88%"
            },
            {
              "name": "离职率",
              "num": "1.57%"
            }
          ]
        }
      ],
      "feeuser": [
        {
          "name": "电销",
          "num": "35,386"
        },
        {
          "name": "渠道",
          "num": "24,464"
        },
        {
          "name": "行业",
          "num": "7,427"
        },
        {
          "name": "自助销售",
          "num": "447"
        }
      ],
      "main": [
        {
          "name": "IP",
          "num": "914,847"
        },
        {
          "name": "PV",
          "num": "4,804,096"
        },
        {
          "name": "UV",
          "num": "1,233,903"
        },
        {
          "name": "收费会员",
          "num": "67,724"
        }
      ]
    }
  }
}
